scoutregiment.py
a/__init__.py
a/py4j_test.py
a/test.py
scoutregiment/__init__.py
scoutregiment/py4j_test.py
scoutregiment/scoutregiment.py
scoutregiment/scoutregiment_forest.py
scoutregiment/scoutregiment_scout.py
scoutregiment/test.py
pyspark_scout_regiment-0.0.13.dist-info/LICENSE
pyspark_scout_regiment-0.0.13.dist-info/METADATA
pyspark_scout_regiment-0.0.13.dist-info/WHEEL
pyspark_scout_regiment-0.0.13.dist-info/top_level.txt
pyspark_scout_regiment-0.0.13.dist-info/RECORD
