Metadata-Version: 2.1
Name: pyspark-scout-regiment
Version: 0.0.13
Summary: pyspark scout regiment
Home-page: https://github.com/JianweiChen/pyspark-scout-regiment
Author: chenjianwei
Author-email: 1572069841@qq.com
License: MIT
Platform: UNKNOWN
License-File: LICENSE
